setup.py
FunEncryptions.egg-info/PKG-INFO
FunEncryptions.egg-info/SOURCES.txt
FunEncryptions.egg-info/dependency_links.txt
FunEncryptions.egg-info/top_level.txt
funencryptions/__init__.py
funencryptions/algorithms.py
funencryptions/image.py
funencryptions/metadata.py
funencryptions/utils.py