Metadata-Version: 1.0
Name: FunEncryptions
Version: 1.0.2
Summary: A collection of string obfuscation algorithms to be used for fun
Home-page: https://github.com/Mezgrman/FunEncryptions
Author: Julian Metzler
Author-email: contact@mezgrman.de
License: AGPLv3
Keywords: fun mystery riddle encryption obfuscation collection tool
Platform: UNKNOWN
